orm_database_sqlite/__init__.py
orm_database_sqlite/orm_database_sqlite.py
orm_database_sqlite/orm_query.py
orm_database_sqlite-0.0.5.dist-info/licenses/LICENSE
orm_database_sqlite-0.0.5.dist-info/METADATA
orm_database_sqlite-0.0.5.dist-info/WHEEL
orm_database_sqlite-0.0.5.dist-info/top_level.txt
orm_database_sqlite-0.0.5.dist-info/RECORD
