Metadata-Version: 2.4
Name: orm_database_sqlite
Version: 0.0.5
Summary: This module is written to launch your programs with any database you want in the shortest time 
Home-page: https://github.com/sisrsis/orm-database
Author: SISRSIS
Author-email: virussisrsis@gmail.com
License: MIT
License-File: LICENSE
Dynamic: author
Dynamic: author-email
Dynamic: description
Dynamic: description-content-type
Dynamic: home-page
Dynamic: license
Dynamic: license-file
Dynamic: summary
